runapp.py
runapp-0.0.3a1.dist-info/DESCRIPTION.rst
runapp-0.0.3a1.dist-info/METADATA
runapp-0.0.3a1.dist-info/RECORD
runapp-0.0.3a1.dist-info/WHEEL
runapp-0.0.3a1.dist-info/entry_points.txt
runapp-0.0.3a1.dist-info/metadata.json
runapp-0.0.3a1.dist-info/top_level.txt
