Metadata-Version: 2.0
Name: runapp
Version: 0.0.3a1
Summary: Allows to build and/or run your application using simple config file
Requires-Dist: yaml
